Workbook

Sheet All Inputs
A1: Securian Annuity Comparison Tool - User Inputs
A2: Instructions: Fill in the fields below to customize your annuity comparison.
A3: Annuitant's Name
A4: Annuitant's Date of Birth
A5: Annuitant's Gender
A6: Annuitant’s Age | B6: Dropdown: Income, Legacy, Protection, Growth
A7: Joint Annuitant's Name (if applicable)
A8: Joint Annuitant's Date of Birth
A9: Joint Annuitant's Gender
A10: Joint Annuitant’s Age
A11: Issue State
A12: Plan Type (Non-Qualified, IRA, Roth-IRA) | B12: User enters age
A13: Product Selection | B13: User enters years
A14: Selected Riders | B14: 100000
A15: Initial Contributions ($) | B15: Enter amount and frequency
A16: Additional Contributions ($) | B16: Fixed Amount / % of Contract / RMD
A17: Contribution Frequency | B17: Non-Qualified / IRA / Roth-IRA
A18: Withdrawals ($ or %) | B18: Select from dropdown
A19: Withdrawal Frequency | B19: List selected riders
A20: Allocation Choices | B20: Enter % allocation strategy
A21: Expected Return Rate (%) | B21: Track historical returns
A22: Years Until Goal | B22: Enter name
A23: Historical Performance Consideration (Yes/No) | B23: MM/DD/YYYY
A24: Desired Goal (Growth, Income, Legacy, Protection) | B24: Male / Female
A25: SecureLink Ultra with Cap Rate (%) | B25: Calculated based on DOB
A26: SecureLink Ultra with Guaranteed Cap Rate (%) | B26: Enter name
... A29: Submit | B29: Calculated based on DOB
A30: Enter SecureLink Ultra 5 S&P 500 Cap Rate (%) | B30: 10.25
A31: Enter SecureLink Ultra 7 S&P 500 Cap Rate (%) | B31: 10.5
A32: Enter SecureLink Chronic Illness Access S&P 500 Cap Rate (%) | B32: 8.5
A33: Enter SecureLink Ultra 5 Inverse Performance Trigger (%) | B33: 6
A34: Enter SecureLink Ultra 7 Inverse Performance Trigger (%) | B34: 6.5
A35: Enter S&P 500 Actual Return for Year (%) | B35: 0
A37: Click 'Submit' to process inputs and refresh all calculations.

Sheet Best Solution
A1: Instructions:
A2: This sheet highlights the best annuity option for Growth, Income, Legacy, and Protection based on user inputs. The highest-performing product in each category is automatically highlighted. | B2: ='All Inputs'!B13
A3: Best Annuity Solution Based on Your Inputs | B3: ='All Inputs'!B3
A4: Your Selected Goal | B4: ='All Inputs'!B4
A5: Your Age | B5: ='All Inputs'!B5
A6: Years Until Goal | B6: ='All Inputs'!B6
A7: Initial Contributions | B7: ='All Inputs'!B7
A8: Best Option for Growth | B8: ='All Inputs'!B8
A9: Best Option for Income | B9: ='All Inputs'!B9
A10: Best Option for Legacy | B10: ='All Inputs'!B10
A11: Best Option for Protection | B11: ='All Inputs'!B11
B12: ='All Inputs'!B12
B13: ='All Inputs'!B13
B14: ='All Inputs'!B14
B15: ='All Inputs'!B15
B16: ='All Inputs'!B16
B17: ='All Inputs'!B17
B18: ='All Inputs'!B18
B19: ='All Inputs'!B19
B20: ='All Inputs'!B20
B21: ='All Inputs'!B21
B22: ='All Inputs'!B22
B23: ='All Inputs'!B23
... B28: ='All Inputs'!B28

Sheet Automated Analysis
A1: Instructions:
A2: This section provides a summary of all key calculations, including the best annuity choice based on inputs. Review for consistency and correctness. | B2: ='All Inputs'!B13
A3: Securian Annuity Comparison - Automated Analysis | B3: ='All Inputs'!B3
A4: Your Selected Goal: | B4: ='All Inputs'!B4
A5: Your Age: | B5: ='All Inputs'!B5
A6: Years Until Goal: | B6: ='All Inputs'!B6
A7: Initial Contributions: | B7: ='All Inputs'!B7
A8: Selected Product: | B8: ='All Inputs'!B8
A9: Selected Riders: | B9: ='All Inputs'!B9
A10: Best Recommended Option for Your Goal: | B10: ='All Inputs'!B10
A11: Projected Growth Rate: | B11: ='All Inputs'!B11
A12: Projected Surrender Value in Year 10: | B12: ='All Inputs'!B12
A13: Legacy Benefit Projection: | B13: ='All Inputs'!B13
B14: ='All Inputs'!B14
B15: ='All Inputs'!B15
B16: ='All Inputs'!B16
B17: ='All Inputs'!B17
B18: ='All Inputs'!B18
B19: ='All Inputs'!B19
B20: ='All Inputs'!B20
B21: ='All Inputs'!B21
B22: ='All Inputs'!B22
B23: ='All Inputs'!B23
B24: ='All Inputs'!B24
B25: ='All Inputs'!B25
... B28: ='All Inputs'!B28

Sheet Growth Calculator
A1: Instructions:
A2: This sheet projects potential annuity growth over time based on user inputs, including SecureLink Ultra crediting rates. Ensure that correct cap rates and participation rates are entered. | B2: ='All Inputs'!B13
A3: Expanded Automated Annuity Comparison Tool | B3: ='All Inputs'!B3
A4: Enter Initial Investment | B4: ='All Inputs'!B4
A5: Enter Expected Net Rate of Return (%) | B5: ='All Inputs'!B5
A6: Enter Number of Years | B6: ='All Inputs'!B6
A7: Enter SecureLink Ultra 7 S&P 500 Participation Rate (%) | B7: ='All Inputs'!B7
A8: Enter SecureLink Chronic Illness Access S&P 500 Cap Rate (%) | B8: ='All Inputs'!B8
A9: Enter MultiOption Momentum Historical Return (%) | B9: ='All Inputs'!B9
A10: Enter Guide B HAV II Net Return (%) | B10: ='All Inputs'!B10
A11: Enter Extra HAV II Net Return (%) | B11: ='All Inputs'!B11
A12: Enter MyPath Journey Roll-Up Rate (%) | B12: ='All Inputs'!B12
A13: Enter Premier Protector Growth Rate (%) | B13: ='All Inputs'!B13
A14: Year | B14: ='All Inputs'!B14 | C14: SecureLink Ultra 7 Surrender Value | D14: SecureLink Ultra 5 Contract Value | E14: SecureLink Ultra 5 Surrender Value | F14: SecureLink Chronic Illness Access Contract Value | G14: SecureLink Chronic Illness Access Surrender Value | H14: MultiOption Momentum Contract Value | I14: MultiOption Momentum Surrender Value | J14: Guide B HAV II Contract Value | K14: Guide B HAV II Surrender Value | L14: Guide B Premier II Contract Value | M14: Guide B Premier II Surrender Value | N14: Extra HAV II Contract Value | O14: Extra HAV II Surrender Value | P14: Extra Premier II Contract Value | Q14: Extra Premier II Surrender Value | R14: Momentum Premier Protector Contract Value | S14: Momentum Premier Protector Surrender Value | T14: MyPath Journey Contract Value | U14: MyPath Journey Surrender Value
A15: 1 | B15: ='All Inputs'!B15 | C15: 153900 | D15: 160000 | E15: 150400 | F15: 108500 | G15: 97650 | H15: 113620 | I15: 105666.6 | J15: 107840 | K15: 99212.8 | L15: 105000 | M15: 95550 | N15: 113240 | O15: 103048.4 | P15: 106000 | Q15: 96460 | R15: 104000 | S15: 95680 | T15: 105000 | U15: 97650
A16: 2 | B16: ='All Inputs'!B16 | C16: 249318 | D16: 256000 | E16: 240640 | F16: 117722.5 | G16: 105950.25 | H16: 129095.04 | I16: 120058.39 | J16: 116294.66 | K16: 106991.08 | L16: 110250 | M16: 100327.5 | N16: 128232.98 | O16: 116692.01 | P16: 112360 | Q16: 102247.6 | R16: 108160 | S16: 99507.2 | T16: 110250 | U16: 102532.5
A17: 3 | B17: ='All Inputs'!B17 | C17: 403895.16 | D17: 409600 | E17: 385024 | F17: 127728.91 | G17: 114956.02 | H17: 146677.79 | I17: 136410.34 | J17: 125412.16 | K17: 115379.18 | L17: 115762.5 | M17: 105343.88 | N17: 145211.02 | O17: 132142.03 | P17: 119101.6 | Q17: 108382.46 | R17: 112486.4 | S17: 103487.49 | T17: 115762.5 | U17: 107659.12
A18: 4 | B18: ='All Inputs'!B18 | C18: 654310.16 | D18: 655360 | E18: 616038.4 | F18: 138585.87 | G18: 124727.28 | H18: 166655.3 | I18: 154989.43 | J18: 135244.47 | K18: 124424.91 | L18: 121550.62 | M18: 110611.07 | N18: 164436.96 | O18: 149637.63 | P18: 126247.7 | Q18: 114885.4 | R18: 116985.86 | S18: 107626.99 | T18: 121550.62 | U18: 113042.08
A19: 5 | B19: ='All Inputs'!B19 | C19: 1059982.5 | D19: 1048576 | E19: 985661.44 | F19: 150365.67 | G19: 135329.1 | H19: 189353.76 | I19: 176098.99 | J19: 145847.64 | K19: 134179.83 | L19: 127628.16 | M19: 116141.62 | N19: 186208.42 | O19: 169449.66 | P19: 133822.56 | Q19: 121778.53 | R19: 121665.29 | S19: 111932.07 | T19: 127628.16 | U19: 118694.19
A20: 6 | B20: ='All Inputs'!B20 | C20: 1717171.6 | D20: 1677721.6 | E20: 1577058.3 | F20: 163146.75 | G20: 146832.08 | H20: 215143.74 | I20: 200083.68 | J20: 157282.09 | K20: 144699.52 | L20: 134009.56 | M20: 121948.7 | N20: 210862.41 | O20: 191884.79 | P20: 141851.91 | Q20: 129085.24 | R20: 126531.9 | S20: 116409.35 | T20: 134009.56 | U20: 124628.89
A21: 7 | B21: ='All Inputs'!B21 | C21: 2781818 | D21: 2684354.6 | E21: 2523293.3 | F21: 177014.22 | G21: 159312.8 | H21: 244446.31 | I21: 227335.07 | J21: 169613.01 | K21: 156043.97 | L21: 140710.04 | M21: 128046.14 | N21: 238780.59 | O21: 217290.34 | P21: 150363.03 | Q21: 136830.35 | R21: 131593.18 | S21: 121065.72 | T21: 140710.04 | U21: 130860.34
A22: 8 | B22: ='All Inputs'!B22 | C22: 4506545.1 | D22: 4294967.3 | E22: 4037269.3 | F22: 192060.43 | G22: 172854.39 | H22: 277739.9 | I22: 258298.11 | J22: 182910.67 | K22: 168277.81 | L22: 147745.54 | M22: 134448.45 | N22: 270395.14 | O22: 246059.58 | P22: 159384.81 | Q22: 145040.17 | R22: 136856.91 | S22: 125908.35 | T22: 147745.54 | U22: 137403.36
A23: 9 | B23: ='All Inputs'!B23 | C23: 7300603.1 | D23: 6871947.7 | E23: 6459630.8 | F23: 208385.57 | G23: 187547.01 | H23: 315568.08 | I23: 293478.31 | J23: 197250.86 | K23: 181470.79 | L23: 155132.82 | M23: 141170.87 | N23: 306195.46 | O23: 278637.87 | P23: 168947.9 | Q23: 153742.59 | R23: 142331.18 | S23: 130944.69 | T23: 155132.82 | U23: 144273.52
A24: 10 | B24: ='All Inputs'!B24 | C24: 11826977 | D24: 10995116 | E24: 10335409 | F24: 226098.34 | G24: 203488.51 | H24: 358548.45 | I24: 333450.06 | J24: 212715.33 | K24: 195698.1 | L24: 162889.46 | M24: 148229.41 | N24: 346735.74 | O24: 315529.52 | P24: 179084.77 | Q24: 162967.14 | R24: 148024.43 | S24: 136182.47 | T24: 162889.46 | U24: 151487.2
A25: If S&P 500 Return is less than Cap Rate, apply actual return. If greater, apply cap. | B25: ='All Inputs'!B25
A26: SecureLink Ultra 5 Interest Credit (%) | B26: ='All Inputs'!B26
A27: SecureLink Ultra 7 Interest Credit (%) | B27: ='All Inputs'!B27
A28: SecureLink Chronic Illness Access Interest Credit (%) | B28: ='All Inputs'!B28
A29: SecureLink Ultra 5 Inverse Performance Credit (%) | B29: =IF(User Inputs!B12<0, User Inputs!B9, 0)
A30: SecureLink Ultra 7 Inverse Performance Credit (%) | B30: =IF(User Inputs!B12<0, User Inputs!B10, 0)

Sheet Surrender & Withdrawal Strategy
A1: Instructions:
A2: This sheet analyzes withdrawal scenarios, factoring in surrender charges and penalty-free access. Verify withdrawal rates and timing for accuracy. | B2: ='All Inputs'!B13
A3: Surrender & Withdrawal Strategy Calculator | B3: ='All Inputs'!B3
A4: Enter Initial Contract Value | B4: ='All Inputs'!B4
A5: Enter Annual Withdrawal Amount (%) | B5: ='All Inputs'!B5
A6: Enter Fixed Annual Withdrawal ($) | B6: ='All Inputs'!B6
A7: Enter Years for Strategy | B7: ='All Inputs'!B7
A8: Year | B8: ='All Inputs'!B8 | C8: SecureLink Ultra 7 Surrender Value | D8: SecureLink Ultra 5 Contract Value | E8: SecureLink Ultra 5 Surrender Value | F8: SecureLink Chronic Illness Access Contract Value | G8: SecureLink Chronic Illness Access Surrender Value | H8: MultiOption Momentum Contract Value | I8: MultiOption Momentum Surrender Value | J8: Guide B Contract Value | K8: Guide B Surrender Value | L8: Extra Contract Value | M8: Extra Surrender Value | N8: SecureOption Choice Contract Value | O8: SecureOption Choice Surrender Value
A9: 1 | B9: ='All Inputs'!B9 | C9: 81900 | D9: 90000 | E9: 81900 | F9: 90000 | G9: 83700 | H9: 90000 | I9: 82800 | J9: 90000 | K9: 82800 | L9: 90000 | M9: 84150 | N9: 90000 | O9: 81900
A10: 2 | B10: ='All Inputs'!B10 | C10: 74520 | D10: 81000 | E10: 74520 | F10: 81000 | G10: 76140 | H10: 81000 | I10: 74520 | J10: 81000 | K10: 74520 | L10: 81000 | M10: 75735 | N10: 81000 | O10: 74520
A11: 3 | B11: ='All Inputs'!B11 | C11: 67797 | D11: 72900 | E11: 67797 | F11: 72900 | G11: 69255 | H11: 72900 | I11: 67797 | J11: 72900 | K11: 67797 | L11: 72900 | M11: 68598.9 | N11: 72900 | O11: 67797
A12: 4 | B12: ='All Inputs'!B12 | C12: 61673.4 | D12: 65610 | E12: 61673.4 | F12: 65610 | G12: 62985.6 | H12: 65610 | I12: 61673.4 | J12: 65610 | K12: 61673.4 | L12: 65610 | M12: 61739.01 | N12: 65610 | O12: 61673.4
A13: 5 | B13: ='All Inputs'!B13 | C13: 56096.55 | D13: 59049 | E13: 56096.55 | F13: 59049 | G13: 57277.53 | H13: 59049 | I13: 56096.55 | J13: 59049 | K13: 56096.55 | L13: 59049 | M13: 55565.109 | N13: 59049 | O13: 56096.55
A14: 6 | B14: ='All Inputs'!B14 | C14: 51018.336 | D14: 53144.1 | E14: 53144.1 | F14: 53144.1 | G14: 52081.218 | H14: 53144.1 | I14: 53144.1 | J14: 53144.1 | K14: 51018.336 | L14: 53144.1 | M14: 50486.895 | N14: 53144.1 | O14: 51018.336
A15: 7 | B15: ='All Inputs'!B15 | C15: 46394.799 | D15: 47829.69 | E15: 47829.69 | F15: 47829.69 | G15: 47351.393 | H15: 47829.69 | I15: 47829.69 | J15: 47829.69 | K15: 46394.799 | L15: 47829.69 | M15: 45916.502 | N15: 47829.69 | O15: 46394.799
A16: 8 | B16: ='All Inputs'!B16 | C16: 42185.787 | D16: 43046.721 | E16: 43046.721 | F16: 43046.721 | G16: 43046.721 | H16: 43046.721 | I16: 43046.721 | J16: 43046.721 | K16: 43046.721 | L16: 43046.721 | M16: 41755.319 | N16: 43046.721 | O16: 43046.721
A17: 9 | B17: ='All Inputs'!B17 | C17: 38354.628 | D17: 38742.049 | E17: 38742.049 | F17: 38742.049 | G17: 38742.049 | H17: 38742.049 | I17: 38742.049 | J17: 38742.049 | K17: 38742.049 | L17: 38742.049 | M17: 37967.208 | N17: 38742.049 | O17: 38742.049
A18: 10 | B18: ='All Inputs'!B18 | C18: 34867.844 | D18: 34867.844 | E18: 34867.844 | F18: 34867.844 | G18: 34867.844 | H18: 34867.844 | I18: 34867.844 | J18: 34867.844 | K18: 34867.844 | L18: 34867.844 | M18: 34867.844 | N18: 34867.844 | O18: 34867.844
B19: ='All Inputs'!B19
B20: ='All Inputs'!B20
B21: ='All Inputs'!B21
B22: ='All Inputs'!B22
B23: ='All Inputs'!B23
B24: ='All Inputs'!B24
B25: ='All Inputs'!B25
B26: ='All Inputs'!B26
B27: ='All Inputs'!B27
B28: ='All Inputs'!B28

Sheet Legacy & Death Benefit
A1: Instructions:
A2: This section compares death benefits and legacy strategies based on selected annuities and riders. Ensure that any roll-up rates or guaranteed growth factors are properly considered. | B2: ='All Inputs'!B13
A3: Legacy & Death Benefit Comparison Calculator | B3: ='All Inputs'!B3
A4: Enter Initial Contract Value | B4: ='All Inputs'!B4
A5: Enter Expected Growth Rate (%) | B5: ='All Inputs'!B5
A6: Enter Number of Years | B6: ='All Inputs'!B6
A7: Enter Annual Withdrawal Amount (%) | B7: ='All Inputs'!B7
A8: Enter Fixed Annual Withdrawal ($) | B8: ='All Inputs'!B8
A9: Year | B9: ='All Inputs'!B9 | C9: Guide B HAV II Death Benefit | D9: Guide B Premier II Contract Value | E9: Guide B Premier II Death Benefit | F9: Extra HAV II Contract Value | G9: Extra HAV II Death Benefit | H9: Momentum Premier Protector Contract Value | I9: Momentum Premier Protector Death Benefit | J9: SecureLink Chronic Illness Access Contract Value | K9: SecureLink Chronic Illness Access Death Benefit | L9: Estate Enhancement Benefit II Contract Value | M9: Estate Enhancement Benefit II Death Benefit
A10: 1 | B10: ='All Inputs'!B10 | C10: 95400 | D10: 99750 | E10: 99473.684 | F10: 101175 | G10: 95850 | H10: 98800 | I10: 98526.316 | J10: 102600 | K10: 110808 | L10: 133000 | M10: 126000
A11: 2 | B11: ='All Inputs'!B11 | C11: 96067.8 | D11: 99500.625 | E11: 98950.139 | F11: 102363.81 | G11: 96976.237 | H11: 97614.4 | I11: 97074.349 | J11: 105267.6 | K11: 113689.01 | L11: 176890 | M11: 167580
A12: 3 | B12: ='All Inputs'!B12 | C12: 96740.275 | D12: 99251.873 | E12: 98429.348 | F12: 103566.58 | G12: 98115.708 | H12: 96443.027 | I12: 95643.78 | J12: 108004.56 | K12: 116644.92 | L12: 235263.7 | M12: 222881.4
A13: 4 | B13: ='All Inputs'!B13 | C13: 97417.457 | D13: 99003.744 | E13: 97911.299 | F13: 104783.49 | G13: 99268.568 | H13: 95285.711 | I13: 94234.292 | J13: 110812.68 | K13: 119677.69 | L13: 312900.72 | M13: 296432.26
A14: 5 | B14: ='All Inputs'!B14 | C14: 98099.379 | D14: 98756.234 | E14: 97395.976 | F14: 106014.69 | G14: 100434.97 | H14: 94142.282 | I14: 92845.577 | J14: 113693.81 | K14: 122789.31 | L14: 416157.96 | M14: 394254.91
A15: 6 | B15: ='All Inputs'!B15 | C15: 98786.074 | D15: 98509.344 | E15: 96883.366 | F15: 107260.37 | G15: 101615.08 | H15: 93012.575 | I15: 91477.326 | J15: 116649.84 | K15: 125981.83 | L15: 553490.09 | M15: 524359.03
A16: 7 | B16: ='All Inputs'!B16 | C16: 99477.577 | D16: 98263.07 | E16: 96373.454 | F16: 108520.68 | G16: 102809.06 | H16: 91896.424 | I16: 90129.239 | J16: 119682.74 | K16: 129257.36 | L16: 736141.81 | M16: 697397.51
A17: 8 | B17: ='All Inputs'!B17 | C17: 100173.92 | D17: 98017.413 | E17: 95866.225 | F17: 109795.79 | G17: 104017.07 | H17: 90793.667 | I17: 88801.019 | J17: 122794.49 | K17: 132618.05 | L17: 979068.61 | M17: 927538.69
A18: 9 | B18: ='All Inputs'!B18 | C18: 100875.14 | D18: 97772.369 | E18: 95361.666 | F18: 111085.89 | G18: 105239.27 | H18: 89704.143 | I18: 87492.372 | J18: 125987.15 | K18: 136066.12 | L18: 1302161.3 | M18: 1233626.5
A19: 10 | B19: ='All Inputs'!B19 | C19: 101581.26 | D19: 97527.938 | E19: 94859.762 | F19: 112391.15 | G19: 106475.83 | H19: 88627.693 | I19: 86203.011 | J19: 129262.81 | K19: 139603.84 | L19: 1731874.5 | M19: 1640723.2
B20: ='All Inputs'!B20
B21: ='All Inputs'!B21
B22: ='All Inputs'!B22
B23: ='All Inputs'!B23
B24: ='All Inputs'!B24
B25: ='All Inputs'!B25
B26: ='All Inputs'!B26
B27: ='All Inputs'!B27
B28: ='All Inputs'!B28

Sheet Annuity Issue Ages & Benefits

Sheet Filter by Age

Sheet Index Crediting Rates
A1: Indexed Product (S&P 500) | B1: User Input: Crediting Rate (%)
A2: SecureLink Chronic Illness Access (S&P 500 Cap) | B2: 8.5
A3: SecureLink Ultra 5 (S&P 500 Cap) | B3: 0
A4: SecureLink Ultra 7 (S&P 500 Cap) | B4: 0
A5: MultiOption Momentum (S&P 500 Cap) | B5: 0

Sheet Visual Analysis
A1: Visual Analysis of Annuity Solutions
A2: Below are graphical representations of the impact of growth and withdrawals based on user inputs.
